AUTHORS
LICENSE
MANIFEST.in
README.rst
setup.cfg
setup.py
django_services/__init__.py
django_services/models.py
django_services.egg-info/PKG-INFO
django_services.egg-info/SOURCES.txt
django_services.egg-info/dependency_links.txt
django_services.egg-info/top_level.txt
django_services/admin/__init__.py
django_services/api/__init__.py
django_services/api/api.py
django_services/api/exceptions.py
django_services/api/models.py
django_services/api/renderers.py
django_services/api/serializers.py
django_services/api/urls.py
django_services/api/utils.py
django_services/api/views.py
django_services/runtests/__init__.py
django_services/runtests/runtests.py
django_services/runtests/settings.py
django_services/service/__init__.py
django_services/service/base.py
django_services/service/core.py
django_services/static/css/docs.css
django_services/templates/api_help.html
django_services/templates/rest_framework/api.html
django_services/tests/__init__.py
django_services/tests/models.py
django_services/tests/test_service.py
django_services/tests/tests.py